optom_tools/__init__.py
optom_tools/__main__.py
optom_tools/main.py
optom_tools/prescription/__init__.py
optom_tools/prescription/exceptions.py
optom_tools/prescription/models.py
optom_tools/prescription/prescription.py
optom_tools/utils/__init__.py
optom_tools/utils/clean_output.py
optom_tools/utils/logger.py
optom_tools/visual_acuity/__init__.py
optom_tools/visual_acuity/exceptions.py
optom_tools/visual_acuity/models.py
optom_tools/visual_acuity/visual_acuity.py
optom_tools-0.2.1.dist-info/LICENSE
optom_tools-0.2.1.dist-info/METADATA
optom_tools-0.2.1.dist-info/WHEEL
optom_tools-0.2.1.dist-info/top_level.txt
optom_tools-0.2.1.dist-info/RECORD
