Metadata-Version: 2.1
Name: optom-tools
Version: 0.2.1
Summary: Providing tools for optometrists.
Author: Shivan Sivakumaran
Author-email: <shivan.sivakumaran@gmail.com>
License: MIT
Project-URL: homepage, https://github.com/shivan-s/optom-tools
Project-URL: repository, https://github.com/shivan-s/optom-tools
Project-URL: changelog, https://github.com/shivan-s/optom-tools/blob/main/CHANGELOG.md
Project-URL: documentation, https://shivan-s.github.io/optom-tools
Keywords: optom,optometry,optometrist,calculations
Classifier: License :: OSI Approved :: MIT License
Classifier: Development Status :: 2 - Pre-Alpha
Classifier: Intended Audience :: Healthcare Industry
Classifier: Natural Language :: English
Classifier: Programming Language :: Python :: 3
Classifier: Programming Language :: Python :: 3 :: Only
Classifier: Programming Language :: Python :: Implementation :: CPython
Requires-Python: >=3.7
License-File: LICENSE
Requires-Dist: rich
Requires-Dist: pydantic
Requires-Dist: typing-extensions
